turms/__init__.py
turms/config.py
turms/errors.py
turms/helpers.py
turms/recurse.py
turms/referencer.py
turms/registry.py
turms/rules.py
turms/run.py
turms/utils.py
turms/cli/__init__.py
turms/cli/main.py
turms/cli/watch.py
turms/parsers/__init__.py
turms/parsers/base.py
turms/parsers/polyfill.py
turms/plugins/__init__.py
turms/plugins/base.py
turms/plugins/enums.py
turms/plugins/fragments.py
turms/plugins/funcs.py
turms/plugins/inputs.py
turms/plugins/objects.py
turms/plugins/operations.py
turms/plugins/strawberry.py
turms/processors/__init__.py
turms/processors/base.py
turms/processors/black.py
turms/processors/disclaimer.py
turms/processors/isort.py
turms/processors/merge.py
turms/stylers/__init__.py
turms/stylers/appender.py
turms/stylers/base.py
turms/stylers/capitalize.py
turms/stylers/default.py
turms/stylers/snake_case.py
turms-0.10.0.dist-info/METADATA
turms-0.10.0.dist-info/WHEEL
turms-0.10.0.dist-info/entry_points.txt
turms-0.10.0.dist-info/licenses/LICENSE
turms-0.10.0.dist-info/RECORD
