Metadata-Version: 2.4
Name: turms
Version: 0.10.0
Summary: graphql-codegen powered by pydantic
Project-URL: Homepage, https://jhnnsrs.github.io/turms
Project-URL: Repository, https://github.com/jhnnsrs/turms
Author-email: jhnnsrs <jhnnsrs@gmail.com>
License-Expression: MIT
License-File: LICENSE
Classifier: Development Status :: 6 - Mature
Classifier: Topic :: Software Development :: Build Tools
Classifier: Topic :: Software Development :: Code Generators
Classifier: Topic :: Software Development :: Libraries :: Python Modules
Classifier: Topic :: Utilities
Classifier: Typing :: Typed
Requires-Python: >=3.10
Requires-Dist: graphql-core<4,>=3.2.0
Requires-Dist: pydantic-settings<3,>=2.5.2
Requires-Dist: pydantic>2
Requires-Dist: pyyaml>=5.3.0
Requires-Dist: requests>=2.32.3
Requires-Dist: rich-click>=1.6
Requires-Dist: rich>=11
Requires-Dist: watchfiles>=0.18.1
Provides-Extra: black
Requires-Dist: black>=22.1.0; extra == 'black'
Provides-Extra: isort
Requires-Dist: isort>=5.10.1; extra == 'isort'
Provides-Extra: merge
Requires-Dist: libcst>=1.4.0; extra == 'merge'
Provides-Extra: watch
Requires-Dist: watchfiles>=0.18.1; extra == 'watch'
